expab/__init__.py
expab/ab_testing.py
expab-0.0.6.dist-info/LICENSE
expab-0.0.6.dist-info/METADATA
expab-0.0.6.dist-info/WHEEL
expab-0.0.6.dist-info/top_level.txt
expab-0.0.6.dist-info/RECORD
