Metadata-Version: 2.2
Name: expab
Version: 0.0.6
Summary: A comprehensive Python library for A/B testing analysis
Home-page: https://github.com/Renarion/expab
Author: Renat/Egor
Author-email: ryunisov0@gmail.com
Classifier: Intended Audience :: Science/Research
Classifier: Topic :: Software Development :: Libraries
Classifier: License :: OSI Approved :: MIT License
Classifier: Programming Language :: Python :: 3
Classifier: Programming Language :: Python :: 3.7
Classifier: Programming Language :: Python :: 3.8
Classifier: Programming Language :: Python :: 3.9
Classifier: Programming Language :: Python :: 3.10
Classifier: Programming Language :: Python :: 3.11
Classifier: Programming Language :: Python :: 3.12
License-File: LICENSE
Requires-Dist: numpy>=1.18.0
Requires-Dist: pandas>=1.0.0
Requires-Dist: matplotlib>=3.0.0
Requires-Dist: scipy>=1.4.0
Requires-Dist: statsmodels>=0.12.0
Requires-Dist: seaborn>=0.11.0
Requires-Dist: tqdm>=4.0.0
Dynamic: author
Dynamic: author-email
Dynamic: classifier
Dynamic: description
Dynamic: description-content-type
Dynamic: home-page
Dynamic: requires-dist
Dynamic: summary
